pymoc/__init__.py
pymoc/modules/SO_ML.py
pymoc/modules/__init__.py
pymoc/modules/column.py
pymoc/modules/equi_column.py
pymoc/modules/psi_SO.py
pymoc/modules/psi_thermwind.py
pymoc/plotting/__init__.py
pymoc/plotting/interp_channel.py
pymoc/plotting/interp_twocol.py
pymoc/utils/__init__.py
pymoc/utils/check_numpy_version.py
pymoc/utils/gridit.py
pymoc/utils/make_array.py
pymoc/utils/make_func.py
py_moc-0.0.1rc5.dist-info/LICENSE
py_moc-0.0.1rc5.dist-info/METADATA
py_moc-0.0.1rc5.dist-info/WHEEL
py_moc-0.0.1rc5.dist-info/top_level.txt
py_moc-0.0.1rc5.dist-info/RECORD
