Metadata-Version: 2.1
Name: py-moc
Version: 0.0.1rc5
Summary: A simple model suite for the MOC
Home-page: https://pymoc.github.io
License: UNKNOWN
Platform: UNKNOWN
Classifier: Programming Language :: Python :: 2.7
Classifier: Programming Language :: Python :: 3
Classifier: License :: OSI Approved :: MIT License
Classifier: Operating System :: OS Independent
